jpl/__init__.py
jpl/labcas/__init__.py
jpl/labcas/svs/VERSION.txt
jpl/labcas/svs/__init__.py
jpl/labcas/svs/svs_edit.py
labcas_svsedit-0.0.1.dist-info/METADATA
labcas_svsedit-0.0.1.dist-info/WHEEL
labcas_svsedit-0.0.1.dist-info/entry_points.txt
labcas_svsedit-0.0.1.dist-info/licenses/LICENSE.md
labcas_svsedit-0.0.1.dist-info/licenses/NOTICE.txt
labcas_svsedit-0.0.1.dist-info/RECORD
