Metadata-Version: 2.4
Name: labcas-svsedit
Version: 0.0.1
Summary: PHI/PII removal tool for SVS files
Project-URL: Homepage, https://github.com/jpl-labcas/svs_edit
Project-URL: Issues, https://github.com/jpl-labcas/svs_edit/issues
Author-email: Ashish Mahabal <aam@astro.caltech.edu>, Sean Kelly <kelly@seankelly.biz>
License: Apache License
License-File: LICENSE.md
License-File: NOTICE.txt
Keywords: archive,cancer,catalog,data,edrn,labcas,phi,pii,svs,tiff
Classifier: Development Status :: 2 - Pre-Alpha
Classifier: Intended Audience :: Healthcare Industry
Classifier: Intended Audience :: Science/Research
Classifier: License :: OSI Approved :: Apache Software License
Classifier: Natural Language :: English
Classifier: Operating System :: OS Independent
Classifier: Programming Language :: Python :: 3
Requires-Python: >=3.12
Requires-Dist: tifftools~=1.6.1
